dialog2rasa/__init__.py
dialog2rasa/cli.py
dialog2rasa/converters/__init__.py
dialog2rasa/converters/base.py
dialog2rasa/converters/core.py
dialog2rasa/converters/entity.py
dialog2rasa/converters/intent.py
dialog2rasa/converters/manager.py
dialog2rasa/converters/slot.py
dialog2rasa/converters/utterance.py
dialog2rasa/utils/__init__.py
dialog2rasa/utils/formatting.py
dialog2rasa/utils/general.py
dialog2rasa/utils/io.py
dialog2rasa-0.1.19.dist-info/LICENSE
dialog2rasa-0.1.19.dist-info/METADATA
dialog2rasa-0.1.19.dist-info/WHEEL
dialog2rasa-0.1.19.dist-info/entry_points.txt
dialog2rasa-0.1.19.dist-info/RECORD
