Metadata-Version: 2.1
Name: dialog2rasa
Version: 0.1.19
Summary: Dialogflow to Rasa > 3.0 agent converter.
License: Apache 2.0
Author: Murilo Bellatini
Requires-Python: >=3.10,<4.0
Classifier: License :: Other/Proprietary License
Classifier: Programming Language :: Python :: 3
Classifier: Programming Language :: Python :: 3.10
Classifier: Programming Language :: Python :: 3.11
Classifier: Programming Language :: Python :: 3.12
Requires-Dist: colorama (>=0.4.6,<0.5.0)
Requires-Dist: pytest (>=8.1.1,<9.0.0)
